LICENSE.md
scraper/DataLoaders/AnnotationDataLoader.py
scraper/DataLoaders/WebDataLoader.py
scraper/DataLoaders/__init__.py
scraper/__init__.py
scraper/augmentations/__init__.py
scraper/augmentations/augs.py
scraper/augmentations/run_augs.py
scraper/google_images/__init__.py
scraper/google_images/config.py
scraper/google_images/crawler.py
scraper/google_images/google.py
scraper/remove_dupes.py
scraper/shutterstock_images/__init__.py
scraper/shutterstock_images/crawler.py
scraper/shutterstock_images/shutterstock.py
scraper/util.py
scraper/yahoo_images/__init__.py
scraper/yahoo_images/crawler.py
scraper/yahoo_images/yahoo.py
utilities/__init__.py
utilities/dataset_setup/__init__.py
utilities/dataset_setup/download_dataset.py
utilities/dataset_setup/setup.py
utilities/optimizers/__init__.py
utilities/optimizers/ram_reducer.py
utilities/output_generation/__init__.py
utilities/output_generation/misc_output.py
utilities/output_generation/output_calculations.py
utilities/parse_config/__init__.py
utilities/parse_config/default_params/__init__.py
utilities/parse_config/default_params/default_annotate.yaml
utilities/parse_config/default_params/default_export.yaml
utilities/parse_config/default_params/default_huggingface.yaml
utilities/parse_config/default_params/default_kaggle.yaml
utilities/parse_config/default_params/default_roboflow.yaml
utilities/parse_config/default_params/default_train_scrape.yaml
utilities/parse_config/get_params_for_job.py
utilities/parse_config/input_validator.py
utilities/parse_config/job_config.py
utilities/pipelines/__init__.py
utilities/pipelines/annotation_loop.py
utilities/pipelines/training_webscrape_loop.py
utilities/yolo_utils/__init__.py
utilities/yolo_utils/train_utils.py
utilities/yolo_utils/yolo_utils.py
flockfysh-0.0.4.dist-info/entry_points.txt
flockfysh-0.0.4.dist-info/LICENSE.md
flockfysh-0.0.4.dist-info/WHEEL
flockfysh-0.0.4.dist-info/METADATA
flockfysh-0.0.4.dist-info/RECORD
