Metadata-Version: 2.1
Name: flockfysh
Version: 0.0.4
Summary: A simple images vending machine that gives more than it gets.
Home-page: https://github.com/teamnebulaco/flockfysh
License: BSD
Keywords: images,flockfysh,dataset,ai,web scraping
Author: Team Nebula
Author-email: teamnebulaco@gmail.com
Requires-Python: >=3.8,<3.12
Classifier: License :: Other/Proprietary License
Classifier: Operating System :: OS Independent
Classifier: Programming Language :: Python :: 3
Classifier: Programming Language :: Python :: 3.8
Classifier: Programming Language :: Python :: 3.9
Classifier: Programming Language :: Python :: 3.10
Classifier: Programming Language :: Python :: 3
Requires-Dist: CacheControl (==0.12.11)
Requires-Dist: GitPython (==3.1.27)
Requires-Dist: Markdown (==3.4.1)
Requires-Dist: MarkupSafe (==2.1.1)
Requires-Dist: Pillow (==9.0.1)
Requires-Dist: PySocks (==1.7.1)
Requires-Dist: PyWavelets (==1.3.0)
Requires-Dist: PyYAML (==6.0)
Requires-Dist: Pygments (==2.12.0)
Requires-Dist: SecretStorage (==3.3.3)
Requires-Dist: Werkzeug (==2.2.1)
Requires-Dist: absl-py (==1.2.0)
Requires-Dist: aiohttp (==3.8.1)
Requires-Dist: aiosignal (==1.2.0)
Requires-Dist: albumentations (==1.2.1)
Requires-Dist: asttokens (==2.0.5)
Requires-Dist: async-timeout (==4.0.2)
Requires-Dist: async_generator (==1.10)
Requires-Dist: attrs (==22.1.0)
Requires-Dist: backcall (==0.2.0)
Requires-Dist: beautifulsoup4 (==4.11.1)
Requires-Dist: bs4 (==0.0.1)
Requires-Dist: cachetools (==5.2.0)
Requires-Dist: cachy (==0.3.0)
Requires-Dist: certifi (==2021.5.30)
Requires-Dist: cffi (==1.15.1)
Requires-Dist: chardet (==4.0.0)
Requires-Dist: charset-normalizer (==2.1.0)
Requires-Dist: cleo (==0.8.1)
Requires-Dist: clikit (==0.6.2)
Requires-Dist: crashtest (==0.3.1)
Requires-Dist: cryptography (==37.0.4)
Requires-Dist: cycler (==0.10.0)
Requires-Dist: datasets (==2.4.0)
Requires-Dist: decorator (==5.1.1)
Requires-Dist: dill (==0.3.5.1)
Requires-Dist: distlib (==0.3.6)
Requires-Dist: executing (==0.9.1)
Requires-Dist: filelock (==3.7.1)
Requires-Dist: fonttools (==4.34.4)
Requires-Dist: frozenlist (==1.3.1)
Requires-Dist: fsspec (==2022.7.1)
Requires-Dist: future (==0.18.2)
Requires-Dist: gitdb (==4.0.9)
Requires-Dist: glob2 (==0.7)
Requires-Dist: google-auth (==2.10.0)
Requires-Dist: google-auth-oauthlib (==0.4.6)
Requires-Dist: grpcio (==1.47.0)
Requires-Dist: h11 (==0.13.0)
Requires-Dist: html5lib (==1.1)
Requires-Dist: huggingface-hub (==0.8.1)
Requires-Dist: idna (==2.10)
Requires-Dist: imageio (==2.21.0)
Requires-Dist: importlib-metadata (==4.12.0)
Requires-Dist: imutils (==0.5.4)
Requires-Dist: ipython (==8.4.0)
Requires-Dist: jedi (==0.18.1)
Requires-Dist: jeepney (==0.8.0)
Requires-Dist: joblib (==1.1.0)
Requires-Dist: kaggle (==1.5.12)
Requires-Dist: keyring (==23.8.2)
Requires-Dist: kiwisolver (==1.3.1)
Requires-Dist: lockfile (==0.12.2)
Requires-Dist: lxml (==4.9.1)
Requires-Dist: matplotlib (==3.5.2)
Requires-Dist: matplotlib-inline (==0.1.3)
Requires-Dist: msgpack (==1.0.4)
Requires-Dist: multidict (==6.0.2)
Requires-Dist: multiprocess (==0.70.13)
Requires-Dist: networkx (==2.8.5)
Requires-Dist: numpy (==1.23.1)
Requires-Dist: oauthlib (==3.2.0)
Requires-Dist: opencv-python (==4.2.0.32)
Requires-Dist: opencv-python-headless (==4.2.0.32)
Requires-Dist: outcome (==1.2.0)
Requires-Dist: packaging (==20.9)
Requires-Dist: pandas (==1.4.3)
Requires-Dist: parso (==0.8.3)
Requires-Dist: pastel (==0.2.1)
Requires-Dist: pefile (==2022.5.30)
Requires-Dist: pexpect (==4.8.0)
Requires-Dist: pickleshare (==0.7.5)
Requires-Dist: pkginfo (==1.8.3)
Requires-Dist: platformdirs (==2.5.2)
Requires-Dist: poetry (==1.1.15)
Requires-Dist: poetry-core (==1.0.8)
Requires-Dist: prompt-toolkit (==3.0.30)
Requires-Dist: protobuf (==3.19.4)
Requires-Dist: psutil (==5.9.1)
Requires-Dist: ptyprocess (==0.7.0)
Requires-Dist: pure-eval (==0.2.2)
Requires-Dist: pyOpenSSL (==22.0.0)
Requires-Dist: pyarrow (==9.0.0)
Requires-Dist: pyasn1 (==0.4.8)
Requires-Dist: pyasn1-modules (==0.2.8)
Requires-Dist: pycparser (==2.21)
Requires-Dist: pylev (==1.4.0)
Requires-Dist: pyparsing (==2.4.7)
Requires-Dist: python-dateutil (==2.8.2)
Requires-Dist: python-dotenv (==0.20.0)
Requires-Dist: python-slugify (==6.1.2)
Requires-Dist: pytz (==2022.1)
Requires-Dist: qudida (==0.0.4)
Requires-Dist: requests (==2.28.1)
Requires-Dist: requests-oauthlib (==1.3.1)
Requires-Dist: requests-toolbelt (==0.9.1)
Requires-Dist: responses (==0.18.0)
Requires-Dist: roboflow (==0.2.11)
Requires-Dist: rsa (==4.9)
Requires-Dist: scikit-image (==0.19.3)
Requires-Dist: scikit-learn (==1.1.1)
Requires-Dist: seaborn (==0.11.2)
Requires-Dist: selenium (==4.3.0)
Requires-Dist: shellingham (==1.5.0)
Requires-Dist: six (==1.16.0)
Requires-Dist: smmap (==5.0.0)
Requires-Dist: sniffio (==1.2.0)
Requires-Dist: sortedcontainers (==2.4.0)
Requires-Dist: soupsieve (==2.3.2.post1)
Requires-Dist: split-folders (==0.5.1)
Requires-Dist: stack-data (==0.3.0)
Requires-Dist: tensorboard (==2.9.1)
Requires-Dist: tensorboard-data-server (==0.6.1)
Requires-Dist: tensorboard-plugin-wit (==1.8.1)
Requires-Dist: text-unidecode (==1.3)
Requires-Dist: threadpoolctl (==3.1.0)
Requires-Dist: tifffile (==2022.8.3)
Requires-Dist: tomlkit (==0.11.4)
Requires-Dist: torch (==1.12.1)
Requires-Dist: torchvision (==0.13.1)
Requires-Dist: tqdm (==4.64.0)
Requires-Dist: traitlets (==5.3.0)
Requires-Dist: trio (==0.21.0)
Requires-Dist: trio-websocket (==0.9.2)
Requires-Dist: typing-extensions (==4.3.0)
Requires-Dist: urllib3 (==1.26.6)
Requires-Dist: validators (==0.20.0)
Requires-Dist: virtualenv (==20.16.3)
Requires-Dist: wcwidth (==0.2.5)
Requires-Dist: webdriver-manager (==3.8.3)
Requires-Dist: webencodings (==0.5.1)
Requires-Dist: wget (==3.2)
Requires-Dist: wsproto (==1.1.0)
Requires-Dist: xxhash (==3.0.0)
Requires-Dist: yarl (==1.8.1)
Requires-Dist: zipp (==3.8.1)
Project-URL: Repository, https://github.com/teamnebulaco/flockfysh
